model/__init__.py
model/building_model.py
preprocess/__init__.py
preprocess/building_preprocess.py
building_energy_forecastor-0.0.1.dist-info/LICENSE
building_energy_forecastor-0.0.1.dist-info/METADATA
building_energy_forecastor-0.0.1.dist-info/WHEEL
building_energy_forecastor-0.0.1.dist-info/top_level.txt
building_energy_forecastor-0.0.1.dist-info/RECORD
