Metadata-Version: 2.1
Name: building-energy-forecastor
Version: 0.0.1
Summary: Pour l'instant fait pas grand chose
Home-page: https://gitlab.com/KZSLAB/building_energy_forecastor.git
Author: Moi Je
Author-email: arthur.feyt@kaizen-solutions.net
License: UNKNOWN
Platform: UNKNOWN
Classifier: Programming Language :: Python :: 3.6
Classifier: License :: OSI Approved :: MIT License
Classifier: Operating System :: OS Independent
Requires-Dist: sklearn
Requires-Dist: numpy
Requires-Dist: pandas
